setup.py
omniprob_distributions/Binomialdistribution.py
omniprob_distributions/Gaussiandistribution.py
omniprob_distributions/Generaldistribution.py
omniprob_distributions/__init__.py
omniprob_distributions.egg-info/PKG-INFO
omniprob_distributions.egg-info/SOURCES.txt
omniprob_distributions.egg-info/dependency_links.txt
omniprob_distributions.egg-info/not-zip-safe
omniprob_distributions.egg-info/top_level.txt