Metadata-Version: 1.0
Name: omniprob-distributions
Version: 0.1
Summary: Gaussian distributions
Home-page: UNKNOWN
Author: ehizzz
Author-email: ehizrendezvouz@gmail.com
License: UNKNOWN
Platform: UNKNOWN
